CHANGES.rst
DESCRIPTION.rst
MANIFEST.in
README.md
setup.py
src/rdh/__init__.py
src/rdh/_argparse.py
src/rdh/_log.py
src/rdh/_redis.py
src/redis_docker_harness.egg-info/PKG-INFO
src/redis_docker_harness.egg-info/SOURCES.txt
src/redis_docker_harness.egg-info/dependency_links.txt
src/redis_docker_harness.egg-info/requires.txt
src/redis_docker_harness.egg-info/top_level.txt