Metadata-Version: 1.1
Name: redis-docker-harness
Version: 0.0.1
Summary: Classes and methods for integrating code inside a docker image into a processing pipeline, using redis for exchanging data.
Home-page: https://github.com/waikato-datamining/redis-docker-harness
Author: Peter Reutemann
Author-email: fracpete@waikato.ac.nz
License: MIT License
Platform: UNKNOWN
Classifier: Development Status :: 4 - Beta
Classifier: License :: OSI Approved :: MIT License
Classifier: Topic :: Scientific/Engineering
Classifier: Programming Language :: Python :: 3
